{"id":13421777,"name":"Kevin Williams","email_address":"wilkevi1@umbc.edu","admin":false,"has_basecamp_siblings":false,"created_at":"2016-02-18T17:01:42.000-05:00","updated_at":"2016-05-18T18:18:30.000-04:00","account_owner":false,"identity_id":13350374,"can_create_projects":true,"avatar_url":"http:\/\/cdn.37img.com\/builtin\/default_avatar_v1_7\/avatar.gif?r=3","fullsize_avatar_url":"https:\/\/cdn.37img.com\/builtin\/default_avatar_v1_7\/original.gif?r=3","events":{"count":0,"updated_at":null,"url":"https:\/\/basecamp.com\/2979808\/api\/v1\/people\/13421777\/events.json","app_url":"https:\/\/basecamp.com\/2979808\/people\/13421777\/events"},"assigned_todos":{"count":0,"updated_at":null,"url":"https:\/\/basecamp.com\/2979808\/api\/v1\/people\/13421777\/assigned_todos.json"},"outstanding_todos":{"count":0}}